README.md
setup.py
src/mmo_tools/__init__.py
src/mmo_tools/consoleModel.py
src/mmo_tools/core.py
src/mmo_tools/utils.py
src/mmo_tools.egg-info/PKG-INFO
src/mmo_tools.egg-info/SOURCES.txt
src/mmo_tools.egg-info/dependency_links.txt
src/mmo_tools.egg-info/top_level.txt