Metadata-Version: 2.1
Name: mmo-tools
Version: 0.2.9
Summary: Thư Viện Hỗ Trợ Viết Tool Facebook Nhanh
Home-page: UNKNOWN
Author: Lam Dinh
Author-email: ldl.contact.booking@gmail.com
License: UNKNOWN
Platform: UNKNOWN
Classifier: Development Status :: 5 - Production/Stable
Classifier: Intended Audience :: Education
Classifier: Operating System :: Microsoft :: Windows :: Windows 10
Classifier: License :: OSI Approved :: MIT License
Classifier: Programming Language :: Python :: 3
Requires-Python: >=3.6
